datasette_sqlite_tg/__init__.py
datasette_sqlite_tg-0.0.1a19.dist-info/METADATA
datasette_sqlite_tg-0.0.1a19.dist-info/WHEEL
datasette_sqlite_tg-0.0.1a19.dist-info/entry_points.txt
datasette_sqlite_tg-0.0.1a19.dist-info/top_level.txt
datasette_sqlite_tg-0.0.1a19.dist-info/RECORD
